<?xml version='1.0'?>
<?xml-stylesheet type='text/xsl' href='../html.xsl'?>
<report doctype="summary">
    <testcase tcid="730a097b-9247-40e5-a0d4-c7f10477c17d" uname="TC03_ValidateAssessmentPageComponentsAndItemsInCACAndCCA_1" runid="e3b81ca8-9844-481a-8214-adb303dd5c18">
        <name>TC03_ValidateAssessmentPageComponentsAndItemsInCACAndCCA</name>
        <description>No description available</description>
        <iteration>1</iteration>
        <day>1</day>
        <totaldays>1</totaldays>
        <starttime>04:08:01</starttime>
        <browserName>Google Chrome</browserName>
        <browserVersion>126.0.6478.127</browserVersion>
        <buildVersion>11102018</buildVersion>
        <status>Fail</status>
        <endtime>04:10:28</endtime>
        <pass>46</pass>
        <fail>1</fail>
        <warning>0</warning>
        <skip>0</skip>
        <rStepCounter>41</rStepCounter>
        <bStepCounter>4</bStepCounter>
        <resultFolderPath>TC03_ValidateAssessmentPageComponentsAndItemsInCACAndCCA_1_040801</resultFolderPath>
        <resultFileName>TC03_ValidateAssessmentPageComponentsAndItemsInCACAndCCA_1_040801</resultFileName>
    </testcase>
    <summary runid="e3b81ca8-9844-481a-8214-adb303dd5c18">
        <title>Automation Testing Execution Result</title>
        <startTime>07-08-2024 04-08-00_PM IST</startTime>
        <endTime>07-08-2024 04-10-28_PM IST</endTime>
        <environment>QA</environment>
        <build>11102018</build>
        <tcpass>0</tcpass>
        <tcfail>1</tcfail>
        <tcwarning>0</tcwarning>
        <tctotal>1</tctotal>
    </summary>
</report>