<?xml version='1.0'?>
<?xml-stylesheet type='text/xsl' href='../html.xsl'?>
<report doctype="summary">
    <testcase tcid="ced3e9e7-ac36-496f-90d2-1e21fa8a042c" uname="TC03_ValidateAssessmentPageComponentsAndItemsInCACAndCCA_1" runid="6bbdfe9c-594b-4aa2-a8ef-5e3e129477c3">
        <name>TC03_ValidateAssessmentPageComponentsAndItemsInCACAndCCA</name>
        <description>No description available</description>
        <iteration>1</iteration>
        <day>1</day>
        <totaldays>1</totaldays>
        <starttime>05:11:46</starttime>
        <browserName>Google Chrome</browserName>
        <browserVersion>126.0.6478.127</browserVersion>
        <buildVersion>11102018</buildVersion>
        <status>Fail</status>
        <endtime>05:14:14</endtime>
        <pass>46</pass>
        <fail>2</fail>
        <warning>0</warning>
        <skip>0</skip>
        <rStepCounter>42</rStepCounter>
        <bStepCounter>4</bStepCounter>
        <resultFolderPath>TC03_ValidateAssessmentPageComponentsAndItemsInCACAndCCA_1_051146</resultFolderPath>
        <resultFileName>TC03_ValidateAssessmentPageComponentsAndItemsInCACAndCCA_1_051146</resultFileName>
    </testcase>
    <summary runid="6bbdfe9c-594b-4aa2-a8ef-5e3e129477c3">
        <title>Automation Testing Execution Result</title>
        <startTime>07-01-2024 05-11-46_PM IST</startTime>
        <endTime>07-01-2024 05-14-14_PM IST</endTime>
        <environment>QA</environment>
        <build>11102018</build>
        <tcpass>0</tcpass>
        <tcfail>1</tcfail>
        <tcwarning>0</tcwarning>
        <tctotal>1</tctotal>
    </summary>
</report>